sumoq/__init__.py
sumoq/__main__.py
sumoq-0.1.0.dist-info/LICENSE
sumoq-0.1.0.dist-info/METADATA
sumoq-0.1.0.dist-info/WHEEL
sumoq-0.1.0.dist-info/entry_points.txt
sumoq-0.1.0.dist-info/top_level.txt
sumoq-0.1.0.dist-info/zip-safe
sumoq-0.1.0.dist-info/RECORD
